MANIFEST.in
README.md
requirements.txt
setup.py
mokito/__init__.py
mokito/collections.py
mokito/documents.py
mokito/errors.py
mokito/fields.py
mokito/geo_fileds.py
mokito/manage.py
mokito/models.py
mokito/tools.py
mokito.egg-info/PKG-INFO
mokito.egg-info/SOURCES.txt
mokito.egg-info/dependency_links.txt
mokito.egg-info/not-zip-safe
mokito.egg-info/requires.txt
mokito.egg-info/top_level.txt
tests/__init__.py
tests/test_collection_fields.py
tests/test_collection_fields_default.py
tests/test_fields.py
tests/test_fields_default.py
tests/test_geo.py
tests/test_models.py
tests/test_none_fields.py
tests/test_orm.py
tests/util.py