Metadata-Version: 1.1
Name: mokito
Version: 0.3.8
Summary: Mokito is an asynchronous ORM for working with MongoDB inside a Tornado app
Home-page: https://github.com/Asmodius/mokito
Author: Asmodius
Author-email: asmodius.a@gmail.com
License: New BSD License
Download-URL: https://github.com/Asmodius/mokito/archive/master.zip
Keywords: mongo mongodb tornado mokito
Platform: UNKNOWN
Classifier: Development Status :: 4 - Beta
Classifier: Intended Audience :: Developers
Classifier: License :: OSI Approved
Classifier: Operating System :: POSIX :: Linux
Classifier: Programming Language :: Python :: 3.6
Classifier: Topic :: Software Development :: Libraries :: Application Frameworks
